{
  "type": "minecraft:crafting_shaped",
  "pattern": [
    "012",
    "345",
    "678"
  ],
  "key": {
    "0": {
      "item": "minecraft:green_dye"
    },
    "1": {
      "item": "minecraft:iron_ingot"
    },
    "2": {
      "item": "minecraft:green_dye"
    },
    "3": {
      "item": "minecraft:green_dye"
    },
    "4": {
      "item": "minecraft:iron_ingot"
    },
    "5": {
      "item": "minecraft:green_dye"
    },
    "6": {
      "item": "minecraft:black_dye"
    },
    "7": {
      "item": "minecraft:iron_ingot"
    },
    "8": {
      "item": "minecraft:yellow_dye"
    }
  },
  "result": {
    "item": "citycraft:green_construction_barrier",
    "count": 3
  }
}